matrix2latex/__init__.py
matrix2latex/latex_tabulizer.py
matrix2latex-0.0.4.dist-info/LICENSE
matrix2latex-0.0.4.dist-info/METADATA
matrix2latex-0.0.4.dist-info/WHEEL
matrix2latex-0.0.4.dist-info/top_level.txt
matrix2latex-0.0.4.dist-info/RECORD
