Metadata-Version: 2.1
Name: matrix2latex
Version: 0.0.4
Summary: A package to help researchers convert matrices and tensors to LaTeX tables.
Home-page: https://github.com/ssaurab/matrix2latex
Author: Saon
Author-email: saonsa@protonmail.com
License: UNKNOWN
Project-URL: Bug Tracker, https://github.com/ssaurab/matrix2latex/issues
Platform: UNKNOWN
Classifier: Programming Language :: Python :: 3
Classifier: License :: OSI Approved :: MIT License
Classifier: Operating System :: OS Independent
Requires-Python: >=3.6
License-File: LICENSE
